
<item>
<title>Los Vigilantes De La Playa</title>
<link>http://streamcloud.eu/dhi3acarl7j1/Baywatch_Los_Vigilantes_De_La_Playa__2017___HDRip_V_Extendida_.avi.html</link>
<thumbnail>https://pics.filmaffinity.com/baywatch-194302457-large.jpg</thumbnail>
<fanart>http://zonasirena.webcindario.com/kodi/fondo1.jpg</fanart>
</item>

<item>
<title>Los Cazafantasmas 1984</title>
<link>http://streamcloud.eu/un7dsgimwz64/Los_Cazafantasmas.avi.html</link>
<thumbnail>http://www.disfrutaesburgos.com/sites/default/files/cazafantasmas.jpg</thumbnail>
<fanart>http://zonadjjavi.webcindario.com/Kodi/fondo2.jpg</fanart>
</item>

<item>
<title>Los Cazafantasmas 2 1989</title>
<link>http://streamcloud.eu/o7ifnphfpudz/Cazafantasmas.2vuda77.1.11.12.avi.html</link>
<thumbnail>http://www.c1n3.org/r/reitman01i/Images/1989%20Ghostbusters%20II%20-%20Cazafantasmas%20II%20(ale)%2001.jpg</thumbnail>
<fanart>http://zonadjjavi.webcindario.com/Kodi/fondo2.jpg</fanart>
</item>

<item>
<title>Los Cazafantasmas 2016 </title>
<link>http://streamcloud.eu/7oz6504yt9ma/Caz4fant4smasBRLiNE.Down.avi.html</link>
<thumbnail>http://image.tmdb.org/t/p/w396/4qnJ1hsMADxzwnOmnwjZTNp0rKT.jpg</thumbnail>
<fanart>http://zonadjjavi.webcindario.com/Kodi/fondo2.jpg</fanart>
</item>	

<item>
<title>Cuatro Bodas y Un Funeral</title>
<link>http://streamcloud.eu/8si3498hffoq/Cuatro_bodas_y_un_funeral.dvdrip.cast.mpg.html</link>
<thumbnail>http://cdn.cinencuentro.com/wp-content/uploads/2015/07/Cuatro_bodas_y_un_funeral.jpg</thumbnail>
<fanart>http://zonadjjavi.webcindario.com/Kodi/fondo2.jpg</fanart>
</item>

<item>
<title>Soltera a los 40</title>
<link>http://streamcloud.eu/ic4brrgg75qw/S0lt3r4_4_l0s_40_HDRip_RD.avi.html</link>
<thumbnail>http://pics.filmaffinity.com/big_stone_gap-550086683-large.jpg</thumbnail>
<fanart>http://zonadjjavi.webcindario.com/Kodi/fondo2.jpg</fanart>
</item>

<item>
<title>Vaya Par De Polis</title>
<link>http://streamcloud.eu/uvtr1j795cac</link>
<thumbnail>http://pics.filmaffinity.com/cop_out_a_couple_of_dicks-732311876-large.jpg</thumbnail>
<fanart>http://zonadjjavi.webcindario.com/Kodi/fondo2.jpg</fanart>
</item> 

<item>
<title>El Super Canguro</title>
<link>http://streamcloud.eu/0ffcroyktyxb/El.super.canguro.2010.HDRip.es.avi.html</link>
<thumbnail>http://es.web.img3.acsta.net/medias/nmedia/18/74/04/83/20124963.jpg</thumbnail>
<fanart>http://zonadjjavi.webcindario.com/Kodi/fondo2.jpg</fanart>
</item> 

<item>
<title>¿En Qué Piensan Las Mujeres?</title>
<link>http://streamcloud.eu/8if22va162s6/En.que.piensan.las.mujeres.2000.DVDRip.es.avi.html</link>
<thumbnail>http://pics.filmaffinity.com/what_women_want-152267653-large.jpg</thumbnail>
<fanart>http://zonadjjavi.webcindario.com/Kodi/fondo2.jpg</fanart>
</item>  

<item>
<title>Casi 300</title> 
<link>http://streamcloud.eu/8n607l5z8brt/Casi.300_DVDRip__Spanish__2008_.avi.html</link> 
<fanart>http://zonadjjavi.webcindario.com/Kodi/fondo2.jpg</fanart> 
<thumbnail>http://pics.filmaffinity.com/meet_the_spartans-255028094-large.jpg</thumbnail> 
<link></link> 
</item>

<item>
<title>Johnny English</title> 
<link>http://streamcloud.eu/2t1kmtxm7zjh</link> 
<fanart>http://zonadjjavi.webcindario.com/Kodi/fondo2.jpg</fanart> 
<thumbnail>http://www.gstatic.com/tv/thumb/movieposters/32279/p32279_p_v8_ad.jpg</thumbnail> 
<link></link> 
</item>

<item>
<title>Johnny English 2 Returns</title> 
<link>http://streamcloud.eu/5s9r76nvmiba</link> 
<fanart>http://zonadjjavi.webcindario.com/Kodi/fondo2.jpg</fanart> 
<thumbnail>http://image.tmdb.org/t/p/w396/hqXDZoiTUziNu11ZvgNILVsymYZ.jpg</thumbnail> 
<link></link> 
</item>

<item>
<title>Un Espía Y Medio </title>
<link>http://streamcloud.eu/5v2di2e0rfma/Un_espia_y_medio_BR-Line_Down.avi.html</link>
<thumbnail>http://www.canalfreak.net/wp-content/uploads/2016/03/Un_Espia_Y_Medio_Poster_Latino_JPosters_phixr.jpg</thumbnail>
<fanart>http://zonadjjavi.webcindario.com/Kodi/fondo2.jpg</fanart>
</item> 

<item>
<title>Agárralo Como Puedas 2 Y Medio</title> 
<link>http://streamcloud.eu/gnd35v8rdol1/Ag__rralo_como_puedas_2_y_medio.DVDR.Castellano.avi.html</link> 
<fanart>http://zonadjjavi.webcindario.com/Kodi/fondo2.jpg</fanart> 
<thumbnail>http://3.bp.blogspot.com/-GSWW4-ek1xM/UYATGMPI7UI/AAAAAAAADTY/i1Licvm4tn4/s1600/Ag%C3%A1rralo+como+puedas+2+y+121.jpg</thumbnail> 
</item>

<item>
<title>Agárralo como puedas 33 1/3. El insulto final</title> 
<link>http://streamcloud.eu/bky4912bvxl8/Agarralocomopuedas331.3.avi.html</link> 
<fanart>http://zonadjjavi.webcindario.com/Kodi/fondo2.jpg</fanart> 
<thumbnail>http://www.peliculasbook.com/_sf/4/18042415.jpg</thumbnail> 
</item>

<item>
<title>Los Padres De Ella 2000</title>
<link>http://streamcloud.eu/1fulj8fje5lj/lospadresdeella-dvdrip-fumi04.avi.html</link>
<thumbnail>http://www.leelibros.com/biblioteca/files/images/los-padres-de-ella.jpg</thumbnail>
<fanart>http://zonadjjavi.webcindario.com/Kodi/fondo2.jpg</fanart>
</item>

<item>
<title>Los padres de El 2004</title>
<link>http://streamcloud.eu/yz2pmqvbvt09/lospadresdeel-dvdrip-fumi04.avi.html</link>
<thumbnail>http://3.bp.blogspot.com/-rYCnYV0kLyw/UIpXRgzEa0I/AAAAAAAABeE/QI2SzfTCQY8/s1600/los+padres+de+el.jpg</thumbnail>
<fanart>http://zonadjjavi.webcindario.com/Kodi/fondo2.jpg</fanart>
</item>

<item>
<title>Ahora los padres son ellos 2010</title>
<link>http://streamcloud.eu/p49hdrtzkvhh/ahoralospadressonellos-dvdrip-fumi04.avi.html</link>
<thumbnail>http://www.labutaca.net/peliculas/wp-content/uploads/2010/08/ahora-los-padres-son-ellos-cartel1.jpg</thumbnail>
<fanart>http://zonadjjavi.webcindario.com/Kodi/fondo2.jpg</fanart>
</item>

<item>
<title>Zoolander </title>
<link>http://streamcloud.eu/iydl6j9z9xvl/Zoolander_un_descerebrado_de_moda.HDrip.avi.html</link>
<thumbnail>http://t2.gstatic.com/images?q=tbn:ANd9GcTSNVaidBcksRzbIxrYyxm-5Oyy_Z5ncdEcvR4R2sz8nzu1jg19</thumbnail>
<fanart>http://zonadjjavi.webcindario.com/Kodi/fondo2.jpg</fanart>
</item>

<item>
<title>Zoolander No. 2</title>
<link>http://streamcloud.eu/5sk757mr7tsz/Z00l4.HD.RD.avi.html</link>
<thumbnail>http://4.bp.blogspot.com/-p-scM7TQHHo/Vl3KFMLabWI/AAAAAAAANe4/HCkWfsNy-ZI/s1600/Zoolander2_Poster_definitivo.jpg_cmyk.jpg</thumbnail>
<fanart>http://zonadjjavi.webcindario.com/Kodi/fondo2.jpg</fanart>
</item>







<channel>
<name>[COLOR orange]•PELICULAS 2015[/COLOR] </name>
<thumbnail> </thumbnail>
<fanart>    </fanart>
<item>

<subchannel>
<name>   </name>
<thumbnail>http://cdn1.pordede.com/content/covers/mediacover-24987-4.png</thumbnail>
<fanart>http://cdn1.pordede.com/content/covers/mediacover-24987-4.png</fanart>
<subitem>

<subitem>
<title>[COLOR yellow]•[/COLOR][COLOR ] El cambiazo[/COLOR][COLOR yellow](2011)[/COLOR][COLOR orange]informacion: Durante la infancia y la adolescencia, Mitch (Ryan Reynolds) y Dave (Jason Bateman) fueron amigos inseparables, pero con el paso de los años se han ido distanciando. Dave es un abogado enganchado al trabajo, se ha casado y tiene tres hijos. Mitch sigue soltero, es bastante inmaduro, trabaja a veces y vive sin ataduras de ningún tipo. Mitch cree que Dave lo tiene todo: una preciosa esposa (Leslie Mann), unos niños que lo adoran y un buen trabajo en un prestigioso bufete. Dave, por su parte, envidia a Mitch porque vive sin estrés ni presión ni obligaciones. Un día, después de compartir una gran borrachera[/COLOR] </title>
<link>http://streamcloud.eu/wf9c323nch27/El_cambiazo.avi</link>
</channel>



<channel>
<name>[COLOR orange]•PELICULAS 2015[/COLOR] </name>
<thumbnail> </thumbnail>
<fanart>    </fanart>
<item>

<subchannel>
<name>[COLOR yellow]•[/COLOR][COLOR ]    [/COLOR][COLOR yellow][/COLOR][/COLOR]</name>
<thumbnail>http://i.imgur.com/auuZpnI.jpg </thumbnail>
<fanart>http://i.imgur.com/auuZpnI.jpg </fanart>
<subitem>

<subitem>
<title>[COLOR yellow]•[/COLOR][COLOR ]AHORA O NUNCA [/COLOR][COLOR yellow](2015)[/COLOR][COLOR orange]informacion: Eva y Alex son una pareja que, tras años de noviazgo, decide casarse en el lugar en el que se enamoraron: un pequeño pueblecito de la campiña inglesa. Los problemas de la boda comienzan cuando una huelga de controladores aéreos impide que el novio y los invitados se reúnan con la novia y su séquito [/COLOR] </title>
<link>http://streamcloud.eu/yvz8dz92msdq/4h0ra.0.n11nc4.HDRip.Down.avi</link>
</channel>




<channel>
<name>[COLOR orange]•PELICULAS 2015[/COLOR] </name>
<thumbnail> </thumbnail>
<fanart>    </fanart>
<item>

<subchannel>
<name>    </name>
<thumbnail>http://i.imgur.com/E2VcHAK.jpg </thumbnail>
<fanart>http://i.imgur.com/E2VcHAK.jpg </fanart>
<subitem>

<subitem>
<title>[COLOR yellow]•[/COLOR][COLOR ]ENTERRANDO A LA EX [/COLOR][COLOR yellow](2014)[/COLOR][COLOR orange]informacion:  Todos hemos tenido alguna antigua pareja que se resiste a aceptar que la relación ha terminado, pero lo que le ocurre a Max va un paso más allá: justo cuando empieza un romance con la encantadora Olivia, su difunta ex novia Evelyn vuelve de la tumba, dispuesta a pasar lo que le quede de “no vida” junto a él. [/COLOR] </title>
<link>http://streamcloud.eu/a6kpmiou7won/EnteALa3x.HD.RD.avi </link>
</channel>




<channel>
<name>[COLOR orange]•PELICULAS 2015[/COLOR] </name>
<thumbnail> </thumbnail>
<fanart>    </fanart>
<item>

<subchannel>
<name>[COLOR yellow]•[/COLOR][COLOR ]    [/COLOR][COLOR yellow][/COLOR][/COLOR]</name>
<thumbnail>https://i.imgur.com/Y8mBvkX.jpg </thumbnail>
<fanart>https://i.imgur.com/Y8mBvkX.jpg </fanart>
<subitem>

<subitem>
<title>[COLOR yellow]•[/COLOR][COLOR ]SANTA'S LITTLE HELPER[/COLOR][COLOR yellow](2015)[/COLOR][COLOR orange]informacion: Después de ser despedido de su trabajo, un charlatán hombre de negocios (The Miz) se prepara para un concurso elfo para convertirse en el próximo segundo al mando de Santa. A través de una serie de ejercicios de entrenamiento riguroso para prepararse, The Miz y otro elfo aspirante (Paige) se enfrentan cara a cara con la esperanza de convertirse en el pequeño ayudante de Santa. [/COLOR] </title>
<link>http://streamcloud.eu/jtp0m6skh4zb/SantLitHelp.HDR.RD.avi </link>
</channel>




<channel>
<name>[COLOR orange]•PELICULAS 2015[/COLOR] </name>
<thumbnail> </thumbnail>
<fanart>    </fanart>
<item>

<subchannel>
<name>[COLOR yellow]•[/COLOR][COLOR ]    [/COLOR][COLOR yellow][/COLOR][/COLOR]</name>
<thumbnail>http://i.imgbox.com/2oLp6JbE.jpg </thumbnail>
<fanart>http://i.imgbox.com/2oLp6JbE.jpg </fanart>
<subitem>

<subitem>
<title>[COLOR yellow]•[/COLOR][COLOR ]SIN HIJOS [/COLOR][COLOR yellow](2015)[/COLOR][COLOR orange]informacion: Gabriel está separado hace cuatro años. Desde entonces Sofía, su hija de ocho años, es el centro de su vida. Negado de plano a intentar una nueva relación amorosa, Gabriel vuelca toda su energía en su hija y en su trabajo. El idilio padre-hija se ve conmocionado por la aparición de Vicky, amor platónico de la adolescencia, transformada ahora en una mujer hermosa, independiente y desenfadada. [/COLOR] </title>
<link>http://streamcloud.eu/i8wiorqhmah0/SinH1j0sHDR.Down.avi </link>
</channel>



<channel>
<name>[COLOR orange]•PELICULAS 2015[/COLOR] </name>
<thumbnail> </thumbnail>
<fanart>    </fanart>
<item>
 
<subchannel>
<name>[COLOR yellow]•[/COLOR][COLOR ]  [/COLOR][COLOR yellow]2015[/COLOR]</name>
<thumbnail>http://i.imgur.com/wdFITlv.jpg</thumbnail>
<fanart>http://i.imgur.com/wdFITlv.jpg/fanart>
<subitem>
 
<subitem>
<title>[COLOR yellow]•[/COLOR][COLOR ]PARANORMAL MOVIE[/COLOR][COLOR yellow](2013)[/COLOR]</title>
<link>http://streamcloud.eu/l2alsk72uty7/ParanormalMovie.DVDRip.Barbie.avi</link>
</channel>



<channel>
<name>[COLOR orange]•PELICULAS 2015[/COLOR] </name>
<thumbnail> </thumbnail>
<fanart>    </fanart>
<item>
 
 
<subchannel>
<name>[COLOR yellow]•[/COLOR][COLOR ]ENTOURAGE (EL SÉQUITO)[/COLOR][COLOR yellow]2015[/COLOR]</name>
<thumbnail>http://pics.filmaffinity.com/Entourage_El_s_quito-910281680-main.jpg</thumbnail>
<fanart>http://pics.filmaffinity.com/Entourage_El_s_quito-910281680-main.jpg</fanart>
<subitem>
 
<subitem>
<title>[COLOR yellow]•[/COLOR][COLOR ]ENTOURAGE (EL SÉQUITO)[/COLOR][COLOR yellow](2014)[/COLOR]</title>
<link>http://streamcloud.eu/4yvks20ybmys/EntoSequitoHD.Caste.avi</link>
</channel>
 



<channel>
<name>[COLOR orange]•PELICULAS 2015[/COLOR] </name>
<thumbnail> </thumbnail>
<fanart>    </fanart>
<item>

<subchannel>
<name>[COLOR yellow]•[/COLOR][COLOR ]Destinos entrelazados[/COLOR][COLOR yellow]2015[/COLOR]</name>
<thumbnail>http://cdn1.pordede.com/content/covers/mediacover-63989-4.png </thumbnail>
<fanart>http://cdn1.pordede.com/content/covers/mediacover-63989-4.png </fanart>
<subitem>

<subitem>
<title>[COLOR yellow]•[/COLOR][COLOR ]    [/COLOR][COLOR yellow](2014)[/COLOR]</title>
<link>http://streamcloud.eu/fxbctjnvl1sc/Encuentros_Entrelazados_2014_HDrip.avi </link>
</channel>




<channel>
<name>[COLOR orange]•PELICULAS 2015[/COLOR] </name>
<thumbnail> </thumbnail>
<fanart>    </fanart>
<item>

<subchannel>
<name>[COLOR yellow]•[/COLOR][COLOR ]Unos días para recordar [/COLOR][COLOR yellow](2014)[/COLOR]</name>
<thumbnail>http://cdn.pordede.com/content/covers/mediacover-62026-4.png </thumbnail>
<fanart>http://cdn.pordede.com/content/covers/mediacover-62026-4.png </fanart>
<subitem>

<subitem>
<title>[COLOR yellow]•[/COLOR][COLOR ]Unos días para recordar [/COLOR][COLOR yellow](2014)[/COLOR]</title>
<link>http://streamcloud.eu/46br1dwus16w/D14sR3corHDR.avi</link>
</channel>



<channel>
<name>[COLOR orange]•PELICULAS 2015[/COLOR] </name>
<thumbnail> </thumbnail>
<fanart>    </fanart>
<item>

<subchannel>
<name>[COLOR yellow]•[/COLOR][COLOR ]Expelled [/COLOR][COLOR yellow](2014)[/COLOR]</name>
<thumbnail>http://cdn1.pordede.com/content/covers/mediacover-57873-4.png </thumbnail>
<fanart>http://cdn1.pordede.com/content/covers/mediacover-57873-4.png </fanart>
<subitem>

<subitem>
<title>[COLOR yellow]•[/COLOR][COLOR ]Expelled [/COLOR][COLOR yellow](2014)[/COLOR]</title>
<link>http://streamcloud.eu/drb72bx6b9i0/3xpelle.HD.RD.avi </link>
</channel>




<channel>
<name>[COLOR orange]• PELICULAS[/COLOR] </name>
<thumbnail> </thumbnail>
<fanart>      </fanart>
<item>

<subchannel>
<name>[COLOR yellow]•[/COLOR][COLOR ]      [/COLOR]
<thumbnail>http://cdn1.pordede.com/content/covers/mediacover-56715-4.png </thumbnail>
<fanart>http://cdn1.pordede.com/content/covers/mediacover-56715-4.png </fanart>
<subitem>

<subitem>
<title>[COLOR yellow]•[/COLOR][COLOR ]Infiltrados en la universidad[/COLOR][COLOR yellow](2015)[/COLOR][COLOR orange]informacion:  La pareja de policías formada por Schmidt y Jenko vuelve a la carga después del éxito de la operación contra la red de narcotraficantes en el instituto. En esta ocasión, los agentes de la ley siguen perteneciendo a la unidad secreta Jump Street y tendrán que infiltrarse en una universidad para llevar a cabo una arriesgada investigación. Una nueva aventura que pondrá a prueba al dúo cada vez mejor compenetrado. [/COLOR]</title>
<link>http://streamcloud.eu/u4jxkpye5i0o/Infiltrados_en_la_Universidad_MicroHD_1080p_AC3_5.1.mkv </link>
</channel>



<channel>
<name>[COLOR orange]•PELICULAS 2015[/COLOR] </name>
<thumbnail> </thumbnail>
<fanart>    </fanart>
<item>

<subchannel>
<name>[COLOR yellow]•[/COLOR][COLOR ]Infiltrados en clase[/COLOR][COLOR yellow]2015[/COLOR]</name>
<thumbnail>http://cdn1.pordede.com/content/covers/mediacover-31757-4.png </thumbnail>
<fanart>http://cdn1.pordede.com/content/covers/mediacover-31757-4.png </fanart>
<subitem>

<subitem>
<title>[COLOR yellow]•[/COLOR][COLOR ]Infiltrados en clase[/COLOR][COLOR yellow](2012)[/COLOR]</title>
<link>http://streamcloud.eu/0gwl9jyss5xy/Infiltrados_en_clase_MicroHD_1080p_AC3_5.1.mkv</link>
</channel>




<channel>
<name>[COLOR orange]•PELICULAS 2015[/COLOR] </name>
<thumbnail> </thumbnail>
<fanart>    </fanart>
<item>

<subchannel>
<name>[COLOR yellow]•[/COLOR][COLOR ]Paul[/COLOR][COLOR yellow]2015[/COLOR]</name>
<thumbnail>http://cdn1.pordede.com/content/covers/mediacover-19819-4.png</thumbnail>
<fanart>http://cdn1.pordede.com/content/covers/mediacover-19819-4.png</fanart>
<subitem>

<subitem>
<title>[COLOR yellow]•[/COLOR][COLOR ]Paul[/COLOR][COLOR yellow](2011)[/COLOR]</title>
<link>http://streamcloud.eu/fbux83qkp85c</link>
</channel>



<channel>
<name>[COLOR orange]•PELICULAS 2015[/COLOR] </name>
<thumbnail> </thumbnail>
<fanart>    </fanart>
<item>

<subchannel>
<name>[COLOR yellow]•[/COLOR][COLOR ]Amor y otras drogas[/COLOR][COLOR yellow]2010[/COLOR]</name>
<thumbnail>http://cdn.pordede.com/content/covers/mediacover-21960-4.png </thumbnail>
<fanart>http://cdn.pordede.com/content/covers/mediacover-21960-4.png </fanart>
<subitem>

<subitem>
<title>[COLOR yellow]•[/COLOR][COLOR ]Amor y otras drogas[/COLOR][COLOR yellow](2010)[/COLOR]</title>
<link>http://streamcloud.eu/kz0aybjym4u2/Amor_y_otras_drogas_DVDRip.avi</link>
</channel>





<channel>
<name>[COLOR orange]•PELICULAS 2015[/COLOR] </name>
<thumbnail> </thumbnail>
<fanart>    </fanart>
<item>

<subchannel>
<name>[COLOR yellow]•[/COLOR][COLOR ]Mil palabras[/COLOR][COLOR yellow]2015[/COLOR]</name>
<thumbnail>http://cdn1.pordede.com/content/covers/mediacover-35031-4.png </thumbnail>
<fanart>http://cdn1.pordede.com/content/covers/mediacover-35031-4.png </fanart>
<subitem>

<subitem>
<title>[COLOR yellow]•[/COLOR][COLOR ]Mil palabras[/COLOR][COLOR yellow](2012)[/COLOR]</title>
<link>http://streamcloud.eu/s7osggsx2ygu/Mil_palabras_HDrip.avi </link>
</channel>




<channel>
<name>[COLOR orange]• COMEDIA[/COLOR] </name>
<thumbnail> </thumbnail>
<fanart>      </fanart>
<item>

<subchannel>
<name>[COLOR yellow]•[/COLOR][COLOR ]Ocho apellidos vascos[/COLOR]</name>
<thumbnail>http://cdn.pordede.com/content/covers/mediacover-56798-4.png</thumbnail>
<fanart>http://cdn.pordede.com/content/covers/mediacover-56798-4.png</fanart>
<subitem>

<subitem>
<title>[COLOR yellow]•[/COLOR][COLOR ]Ocho apellidos vascos[/COLOR][COLOR yellow](2014)[/COLOR]</title>
<link>http://streamcloud.eu/oncgshrruh28/OchoApellidosVascos-.avi</link>
</channel>




<channel>
<name>[COLOR orange]• COMEDIA[/COLOR] </name>
<thumbnail> </thumbnail>
<fanart>      </fanart>
<item>

<subchannel>
<name>[COLOR yellow]•[/COLOR][COLOR ]Cómo sobrevivir a una despedida/COLOR]</name>
<thumbnail>http://cdn.pordede.com/content/covers/mediacover-60194-4.png </thumbnail>
<fanart>http://cdn.pordede.com/content/covers/mediacover-60194-4.png </fanart>
<subitem>

<subitem>
<title>[COLOR yellow]•[/COLOR][COLOR ]Cómo sobrevivir a una despedida[/COLOR][COLOR yellow](2015)[/COLOR]</title>
<link>http://streamcloud.eu/3hpnuv0hf9en/C.0mo.S.0br.D.3soedda.2015.DVDRip.avi </link>
</channel>





<channel>
<name>[COLOR orange]• COMEDIA[/COLOR] </name>
<thumbnail> </thumbnail>
<fanart>      </fanart>
<item>



<channel>
<name>[COLOR orange]• COMEDIA[/COLOR] </name>
<thumbnail> </thumbnail>
<fanart>      </fanart>
<item>

<subchannel>
<name>[COLOR yellow]•[/COLOR][COLOR ]Dos ladrones y medio[/COLOR][COLOR yellow](2006)[/COLOR]</name>
<thumbnail>http://cdn1.pordede.com/content/covers/mediacover-12877-4.png</thumbnail>
<fanart>http://cdn1.pordede.com/content/covers/mediacover-12877-4.png</fanart>
<subitem>
 
<subitem>
<title>[COLOR yellow]•[/COLOR][COLOR ]Dos ladrones y medio[/COLOR][COLOR yellow](2006)[/COLOR]</title>
<link>http://streamcloud.eu/0x50gt984xup/DOS_LADRON3S_Y_M3DIO_2006__720pDVDR__Castellano_SubAux.avi</link>
</channel>





<channel>
<name>[COLOR orange]• COMEDIA[/COLOR] </name>
<thumbnail> </thumbnail>
<fanart>      </fanart>
<item>
 
<subchannel>
<name>[COLOR yellow]•[/COLOR][COLOR ]Espías[/COLOR][COLOR yellow](2015)[/COLOR]</name>
<thumbnail>http://cdn.pordede.com/content/covers/mediacover-59992-4.png</thumbnail>
<fanart>http://cdn.pordede.com/content/covers/mediacover-59992-4.png</fanart>
<subitem>
 
<subitem>
<title>[COLOR yellow]•[/COLOR][COLOR ]Espías[/COLOR][COLOR yellow](2015)[/COLOR]</title>
<link>http://streamcloud.eu/4jwf4t46lmds/Espias.mp4</link>
</channel>





<channel>
<name>[COLOR orange]• COMEDIA[/COLOR] </name>
<thumbnail> </thumbnail>
<fanart>      </fanart>
<item>
 
<subchannel>
<name>[COLOR yellow]•[/COLOR][COLOR ]With This Ring[/COLOR][COLOR yellow](2015)[/COLOR]</name>
<thumbnail>http://cdn1.pordede.com/content/covers/mediacover-61179-4.png</thumbnail>
<fanart>http://cdn1.pordede.com/content/covers/mediacover-61179-4.png</fanart>
<subitem>
 
<subitem>
<title>[COLOR yellow]•[/COLOR][COLOR ]With This Ring[/COLOR][COLOR yellow](2015)[/COLOR]</title>
<link>http://streamcloud.eu/vwb79u6d680u/W1thTh1sR1ngHDR.avi</link>
</channel> 





<channel>
<name>[COLOR orange]• COMEDIA[/COLOR] </name>
<thumbnail> </thumbnail>
<fanart>      </fanart>
<item>

<subchannel>
<name>[COLOR yellow]•[/COLOR][COLOR ]El club de los incomprendidos[/COLOR]</name>
<thumbnail>http://cdn1.pordede.com/content/covers/mediacover-57549-4.png </thumbnail>
<fanart>http://cdn1.pordede.com/content/covers/mediacover-57549-4.png </fanart>
<subitem>

<subitem>
<title>[COLOR yellow]•[/COLOR][COLOR ]El club de los incomprendidos[/COLOR][COLOR yellow](2014)[/COLOR]</title>
<link>http://streamcloud.eu/zi01y8r9b9mr/El_club_de_los_incomprendidos_DVDR_2014.mp4 </link>
</channel>




<channel>
<name>[COLOR orange]• COMEDIA[/COLOR] </name>
<thumbnail> </thumbnail>
<fanart>      </fanart>
<item>

<subchannel>
<name>[COLOR yellow]•[/COLOR][COLOR ]Ted 2[/COLOR]</name>
<thumbnail>http://cdn1.pordede.com/content/covers/mediacover-59247-4.png </thumbnail>
<fanart>http://cdn1.pordede.com/content/covers/mediacover-59247-4.png </fanart>
<subitem>

<subitem>
<title>[COLOR yellow]•[/COLOR][COLOR ]Ted 2 [/COLOR][COLOR yellow](2015)[/COLOR]</title>
<link>http://streamcloud.eu/tjpoli75an0z/Td2brscrnrspa__www.newpct1.com_.avi</link>
</channel>





<name>[COLOR orange]• COMEDIA[/COLOR]</name>
<thumbnail> </thumbnail>
<fanart>      </fanart>
<item>
 
<subchannel>
<name>[COLOR yellow]•[/COLOR][COLOR ]Negocios con resaca[/COLOR]</name>
<thumbnail>http://cdn1.pordede.com/content/covers/mediacover-57779-4.png</thumbnail>
<fanart>http://cdn1.pordede.com/content/covers/mediacover-57779-4.png</fanart>
<subitem>
 
<subitem>
<title>[COLOR yellow]•[/COLOR][COLOR ]Negocios con resaca[/COLOR][COLOR yellow](2015)[/COLOR]</title>
<link>http://streamcloud.eu/yiax8dqmwjw8/Neg0RekHDR.avi</link>
</channel>     




<name>[COLOR orange]• COMEDIA[/COLOR]</name>
<thumbnail> </thumbnail>
<fanart>      </fanart>
<item>
 
<subchannel>
<name>[COLOR yellow]•[/COLOR][COLOR ]Torrente 5: Operación Eurovegas[/COLOR]</name>
<thumbnail>http://cdn.pordede.com/content/covers/mediacover-57140-4.png</thumbnail>
<fanart>http://cdn.pordede.com/content/covers/mediacover-57140-4.png</fanart>
<subitem>
 
<subitem>
<title>[COLOR yellow]•[/COLOR][COLOR ]Torrente 5: Operación Eurovegas[/COLOR]</title>
<link>http://streamcloud.eu/ol3ij1dur8r5/T0RMEN.FIVE._2014_.BDRip.x264.m1080p.AC3.5.1.Castellano.Forzados._XKlusiveDD_.mkv</link>
</channel>


<channel>
<name>[COLOR orange]• COMEDIA[/COLOR] </name>
<thumbnail> </thumbnail>
<fanart>      </fanart>
<item>
 
<subchannel>
<name>[COLOR yellow]•[/COLOR][COLOR ]Pisándonos los tacones[/COLOR]</name>
<thumbnail>https://sp.yimg.com/xj/th?id=OIP.M5e0f85d00ff96f8b8b4f9319d88fe646o0&pid=15.1&P=0&w=300&h=300</thumbnail>
<fanart>https://sp.yimg.com/xj/th?id=OIP.M5e0f85d00ff96f8b8b4f9319d88fe646o0&pid=15.1&P=0&w=300&h=300</fanart>
<subitem>

<subitem>
<title>[COLOR yellow]•[/COLOR][COLOR ]Pisándonos los tacones[/COLOR][COLOR yellow](2015)[/COLOR]</title>
<link>http://streamcloud.eu/3xi4k6wni9h8/PisanTaco.HDR.RD.avi</link>
</channel>




<channel>
<name>[COLOR orange]• COMEDIA[/COLOR] </name>
<thumbnail> </thumbnail>
<fanart>      </fanart>
<item>
 
<subchannel>
<name>[COLOR yellow]•[/COLOR][COLOR ]Anacleto: Agente secreto[/COLOR]</name>
<thumbnail>https://encrypted-tbn1.gstatic.com/images?q=tbn:ANd9GcQYTyHSHbtJsQjC16d6xLY1lAUk9t3OWWGOh5QkL-ypVICPT2KZTw</thumbnail>
<fanart>https://encrypted-tbn1.gstatic.com/images?q=tbn:ANd9GcQYTyHSHbtJsQjC16d6xLY1lAUk9t3OWWGOh5QkL-ypVICPT2KZTw</fanart>
<subitem>
 
<subitem>
<title>[COLOR yellow]•[/COLOR][COLOR ]Anacleto: Agente secreto[/COLOR][COLOR yellow](2015)[/COLOR]</title>
<link>http://streamcloud.eu/w5g1tx2l8n64/Anacletbrspa.avi</link>
</channel>

 



<channel>
<name>[COLOR orange]• COMEDIA[/COLOR] </name>
<thumbnail> </thumbnail>
<fanart>      </fanart>
<item>
 
 
<subchannel>
<name>[COLOR yellow]•[/COLOR][COLOR ]Pos eso[/COLOR]</name>
<thumbnail>http://cdn.pordede.com/content/covers/mediacover-60938-4.png</thumbnail>
<fanart>http://cdn.pordede.com/content/covers/mediacover-60938-4.png</fanart>
<subitem>
 
 
<subitem>
<title>[COLOR yellow]•[/COLOR][COLOR ]Pos eso[/COLOR][COLOR yellow](2014)[/COLOR]</title>
<link>http://streamcloud.eu/83lpr5ev68wo/P0S3S0.m720p.YK.mkv</link>
</channel>
